README.rst
setup.py
src/fc_simesh_matplotlib/__init__.py
src/fc_simesh_matplotlib/demos.py
src/fc_simesh_matplotlib/siMesh.py
src/fc_simesh_matplotlib/siMeshElt.py
src/fc_simesh_matplotlib.egg-info/PKG-INFO
src/fc_simesh_matplotlib.egg-info/SOURCES.txt
src/fc_simesh_matplotlib.egg-info/dependency_links.txt
src/fc_simesh_matplotlib.egg-info/requires.txt
src/fc_simesh_matplotlib.egg-info/top_level.txt