Metadata-Version: 1.1
Name: fc-simesh-matplotlib
Version: 0.0.1
Summary: Matplotlib add-on to the fc_simesh package
Home-page: http://www.math.univ-paris13.fr/~cuvelier/software
Author: Francois Cuvelier
Author-email: cuvelier@math.univ-paris13.fr
License: BSD
Platform: Linux
Classifier: Topic :: Scientific/Engineering
